Metadata-Version: 1.1
Name: ipapi
Version: 0.5.1
Summary: Python bindings for ipapi (IP address to location mapping service. Free & paid API for a secure, fast & reliable IP lookup (city, country, latitude, longitude, timezone &amp; hostname) - https://ipapi.co)
Home-page: https://github.com/ipapi-co/ipapi-python
Author: ipapi
Author-email: pweb@ipapi.co
License: MIT License
Download-URL: https://github.com/ipapi-co/ipapi-python/archive/0.4.2.tar.gz
Keywords: geolocation,ip address,ip address geolocation,ip address lookup,ip address to location,ip address tracer,ip address tracker,ip checker,ip lookup,ip tracker,ip-address,ipapi,ipapi.co,ipv4,ipv6,location,lookup ip address,trace ip address
Platform: UNKNOWN
